rohdeschwarz/__init__.py
rohdeschwarz/version.py
rohdeschwarz/yaml.py
rohdeschwarz/bin/__init__.py
rohdeschwarz/bin/instr.py
rohdeschwarz/bin/nge.py
rohdeschwarz/bin/ngu.py
rohdeschwarz/bin/osp.py
rohdeschwarz/bin/vna.py
rohdeschwarz/bin/vsa.py
rohdeschwarz/bin/vsg.py
rohdeschwarz/bus/__init__.py
rohdeschwarz/bus/tcp.py
rohdeschwarz/bus/visa.py
rohdeschwarz/bus/mixins/__init__.py
rohdeschwarz/bus/mixins/query.py
rohdeschwarz/general/__init__.py
rohdeschwarz/general/general.py
rohdeschwarz/instruments/__init__.py
rohdeschwarz/instruments/genericinstrument.py
rohdeschwarz/instruments/mixins/__init__.py
rohdeschwarz/instruments/mixins/scpi/__init__.py
rohdeschwarz/instruments/mixins/scpi/helpers.py
rohdeschwarz/instruments/mixins/scpi/scpi.py
rohdeschwarz/instruments/mixins/scpi/method/__init__.py
rohdeschwarz/instruments/mixins/scpi/method/inputs.py
rohdeschwarz/instruments/mixins/scpi/method/method.py
rohdeschwarz/instruments/mixins/scpi/property/__init__.py
rohdeschwarz/instruments/mixins/scpi/property/get.py
rohdeschwarz/instruments/mixins/scpi/property/property.py
rohdeschwarz/instruments/mixins/scpi/property/set.py
rohdeschwarz/instruments/mixins/scpi/types/__init__.py
rohdeschwarz/instruments/mixins/scpi/types/state.py
rohdeschwarz/instruments/mixins/scpi/types/types.py
rohdeschwarz/instruments/ospswitch/__init__.py
rohdeschwarz/instruments/ospswitch/enums.py
rohdeschwarz/instruments/ospswitch/ospswitch.py
rohdeschwarz/instruments/powersupply/__init__.py
rohdeschwarz/instruments/powersupply/nge/__init__.py
rohdeschwarz/instruments/powersupply/nge/channel.py
rohdeschwarz/instruments/powersupply/nge/nge.py
rohdeschwarz/instruments/powersupply/ngu/__init__.py
rohdeschwarz/instruments/powersupply/ngu/channel.py
rohdeschwarz/instruments/powersupply/ngu/ngu.py
rohdeschwarz/instruments/vna/__init__.py
rohdeschwarz/instruments/vna/calunit.py
rohdeschwarz/instruments/vna/channel.py
rohdeschwarz/instruments/vna/diagram.py
rohdeschwarz/instruments/vna/filesystem.py
rohdeschwarz-1.21.0.dist-info/LICENSE.md
rohdeschwarz-1.21.0.dist-info/METADATA
rohdeschwarz-1.21.0.dist-info/WHEEL
rohdeschwarz-1.21.0.dist-info/entry_points.txt
rohdeschwarz-1.21.0.dist-info/top_level.txt
rohdeschwarz-1.21.0.dist-info/RECORD
